ttork/__init__.py
ttork/__main__.py
ttork/__version__.py
ttork/app.py
ttork/cli.py
ttork/ttork.tcss
ttork/models/__init__.py
ttork/models/_k8s_containers.py
ttork/models/_k8s_deployments.py
ttork/models/_k8s_pods.py
ttork/models/_k8s_resource_data.py
ttork/network/__init__.py
ttork/network/_k8s_service.py
ttork/network/_tilt_service.py
ttork/utilities/__init__.py
ttork/utilities/_config.py
ttork/utilities/_config_test.py
ttork/utilities/_time.py
ttork/utilities/_time_test.py
ttork/widgets/__init__.py
ttork/widgets/_confirmation_dialog.py
ttork/widgets/_k8s_container_logs.py
ttork/widgets/_k8s_resource_table.py
ttork/widgets/_resource_text_area.py
ttork/widgets/_tilt_status_tree.py
ttork-0.4.2.dist-info/METADATA
ttork-0.4.2.dist-info/WHEEL
ttork-0.4.2.dist-info/entry_points.txt
ttork-0.4.2.dist-info/licenses/LICENSE
ttork-0.4.2.dist-info/RECORD
