Metadata-Version: 2.3
Name: ttork
Version: 0.4.2
Summary: Textual Tilt Orkestrator: Multiple-Repository Tilt Orchestration Tool.
Project-URL: Homepage, https://github.com/SwordOfDamocles/ttork
Project-URL: Documentation, https://github.com/SwordOfDamocles/ttork
Project-URL: Repository, https://github.com/SwordOfDamocles/ttork
Project-URL: Bug Tracker, https://github.com/SwordOfDamocles/ttork/issues
Project-URL: Changelog, https://github.com/SwordOfDamocles/ttork/blob/master/CHANGELOG.md
Author-email: Andy Waller <awaller@gmail.com>
Maintainer-email: Andy Waller <awaller@gmail.com>
License:                     GNU GENERAL PUBLIC LICENSE
License-File: LICENSE
Keywords: Docker,Kubernetes,Tilt,k8s,ttork
Classifier: Development Status :: 2 - Pre-Alpha
Classifier: Programming Language :: Python :: 3.10
Classifier: Programming Language :: Python :: 3.11
Classifier: Programming Language :: Python :: 3.12
Requires-Python: >=3.10
Requires-Dist: kubernetes
Requires-Dist: pyyaml
Requires-Dist: requests
Requires-Dist: textual
